[
{
"地名": "傲来国",
"介绍": "海外仙国，近海，孙悟空出生前猴群聚居地。 (1回)",
"所属大洲": "东胜神洲"
},
{
"地名": "花果山",
"介绍": "灵山福地，十洲祖脉，三岛龙脉，孙悟空诞生及称王处，奇峰怪石、灵泉异果。 (1回)",
"所属大洲": "东胜神洲"
},
{
"地名": "水帘洞",
"介绍": "花果山中瀑布洞天，猴王洞府，石室齐全，铭“花果山福地，水帘洞洞天”。 (1-2回)",
"所属大洲": "东胜神洲"
},
{
"地名": "蓬莱山",
"介绍": "东海仙岛，孙悟空寻仙途中提及，神仙聚居。 (2回)",
"所属大洲": "东胜神洲"
},
{
"地名": "方丈岛",
"介绍": "东海神岛，仙人炼丹处，孙悟空漂洋过海途经。 (2回)",
"所属大洲": "东胜神洲"
},
{
"地名": "瀛洲",
"介绍": "东海大洲，面积七十万里，孙悟空游方时过。 (2回)",
"所属大洲": "东胜神洲"
},
{
"地名": "祖洲",
"介绍": "东海仙洲，道教十洲之一，孙悟空寻长生路过。 (2回)",
"所属大洲": "东胜神洲"
},
{
"地名": "生洲",
"介绍": "东海灵洲，仙气充裕，孙悟空海上漂流处。 (2回)",
"所属大洲": "东胜神洲"
},
{
"地名": "亶洲",
"介绍": "东海古洲，历史记载仙山，孙悟空游历地。 (2回)",
"所属大洲": "东胜神洲"
},
{
"地名": "夷洲",
"介绍": "东海岛洲，近台湾原型，孙悟空东海漂筏处。 (2回)",
"所属大洲": "东胜神洲"
},
{
"地名": "侏儒国",
"介绍": "东海小国，人矮如侏儒，孙悟空游方遇奇民。 (2回)",
"所属大洲": "东胜神洲"
},
{
"地名": "黑齿国",
"介绍": "东海怪国，人齿黑奇异，孙悟空海上奇遇地。 (2回)",
"所属大洲": "东胜神洲"
},
{
"地名": "白民国",
"介绍": "东海白肤国，居民肤白如雪，孙悟空游历。 (2回)",
"所属大洲": "东胜神洲"
},
{
"地名": "裸国",
"介绍": "东海裸民国，人不穿衣，孙悟空见风俗奇异。 (2回)",
"所属大洲": "东胜神洲"
},
{
"地名": "北俱芦洲",
"介绍": "北方大洲，性拙情疏，好杀生但无贪婪，人寿长，佛祖评“人人固寿”。 (1、13回)",
"所属大洲": "北俱芦洲"
},
{
"地名": "西牛贺洲",
"介绍": "西方大洲，不贪不杀，养气潜灵，佛国多妖，取经终点灵山所在。 (1、13、55回后)",
"所属大洲": "西牛贺洲"
},
{
"地名": "灵台方寸山",
"介绍": "仙山，道场所在，须菩提祖师居，孙悟空学艺处。 (2回)",
"所属大洲": "西牛贺洲"
},
{
"地名": "斜月三星洞",
"介绍": "方寸山洞府，菩提祖师讲道地，孙悟空拜师学七十二变。 (2回)",
"所属大洲": "西牛贺洲"
},
{
"地名": "乌斯庄",
"介绍": "猪八戒原籍庄子，田园村落，悟空寻徒处。 (19-20回)",
"所属大洲": "西牛贺洲"
},
{
"地名": "西梁女国",
"介绍": "女国，全女无男，饮子母河水怀孕，唐僧误饮险生子。 (53-54回)",
"所属大洲": "西牛贺洲"
},
{
"地名": "祭赛国",
"介绍": "祭祀国，国王祈雨，唐僧师徒助降雨除旱魃。 (55-56回)",
"所属大洲": "西牛贺洲"
},
{
"地名": "小西天",
"介绍": "假雷音寺，罗刹女设幻境骗经，唐僧险中计。 (56-57回)",
"所属大洲": "西牛贺洲"
},
{
"地名": "朱紫国",
"介绍": "紫衣国，国王眼病，唐僧祈福治疾。 (58回)",
"所属大洲": "西牛贺洲"
},
{
"地名": "狮驼国",
"介绍": "狮驼岭国，三妖统治，食人无数，唐僧被俘。 (74-77回)",
"所属大洲": "西牛贺洲"
},
{
"地名": "狮驼岭",
"介绍": "狮驼国山岭，三妖巢穴，青狮、白象、大鹏盘踞。 (74回)",
"所属大洲": "西牛贺洲"
},
{
"地名": "狮驼洞",
"介绍": "狮驼岭妖洞，肉山宴客处，唐僧师徒遇险。 (74回)",
"所属大洲": "西牛贺洲"
},
{
"地名": "比丘国",
"介绍": "比丘寺国，国王误杀僧人，设虎狼宴，唐僧辨真相。 (73回)",
"所属大洲": "西牛贺洲"
},
{
"地名": "镇河寺",
"介绍": "比丘国古寺，僧人被杀地，唐僧宿处。 (73回)",
"所属大洲": "西牛贺洲"
},
{
"地名": "灭法国",
"介绍": "灭佛国，原杀僧万名，后改钦法国，唐僧渡心难。 (81-82回)",
"所属大洲": "西牛贺洲"
},
{
"地名": "凤仙郡",
"介绍": "天竺外郡，隐雾山所在，唐僧近终点遇难。 (98回)",
"所属大洲": "西牛贺洲"
},
{
"地名": "隐雾山",
"介绍": "凤仙郡大山，雾气缭绕，近天竺，唐僧最后劫。 (98回)",
"所属大洲": "西牛贺洲"
},
{
"地名": "天竺国",
"介绍": "西天佛国，真假公主劫，唐僧取经终点。 (98-100回)",
"所属大洲": "西牛贺洲"
},
{
"地名": "灵山",
"介绍": "雷音寺所在，佛祖道场，真经取处，师徒功成地。 (99-100回)",
"所属大洲": "西牛贺洲"
},
{
"地名": "芭蕉洞",
"介绍": "铁扇公主洞府，牛魔王妻居，悟空借扇处。 (59-61回)",
"所属大洲": "西牛贺洲"
},
{
"地名": "积雷山",
"介绍": "雷鸣山，牛魔王芭蕉洞附近，悟空大战牛王。 (61回)",
"所属大洲": "西牛贺洲"
},
{
"地名": "摩云洞",
"介绍": "牛魔王洞府，积雷山中，七圣聚会地。 (59回)",
"所属大洲": "西牛贺洲"
},
{
"地名": "毒敌山",
"介绍": "蝎子精巢山，毒钩难敌，观音收妖处。 (55回)",
"所属大洲": "西牛贺洲"
},
{
"地名": "陷空山",
"介绍": "无底洞山，鼠精夫妇居，唐僧遇鼠婚难。 (82-83回)",
"所属大洲": "西牛贺洲"
},
{
"地名": "无底洞",
"介绍": "陷空山鼠洞，百眼魔君旧居，鼠精藏身。 (82回)",
"所属大洲": "西牛贺洲"
},
{
"地名": "玉华县",
"介绍": "天竺东县，城中布金圣母设难，唐僧化缘。 (84-85回)",
"所属大洲": "西牛贺洲"
},
{
"地名": "豹头山",
"介绍": "竹节山，豹头妖盘踞，唐僧遇虎豹难。 (86回)",
"所属大洲": "西牛贺洲"
},
{
"地名": "竹山",
"介绍": "竹节山，十八劲节妖精居，悟空大战。 (86回)",
"所属大洲": "西牛贺洲"
},
{
"地名": "玄英洞",
"介绍": "竹山妖洞，十八公妖巢，唐僧被绑。 (86回)",
"所属大洲": "西牛贺洲"
},
{
"地名": "红水河",
"介绍": "九曲黄河，红孩儿盘踞，唐僧渡河遇火。 (40-42回)",
"所属大洲": "西牛贺洲"
},
{
"地名": "火云洞",
"介绍": "红水河洞，红孩儿圣婴居，观音收服。 (40回)",
"所属大洲": "西牛贺洲"
},
{
"地名": "枯松涧",
"介绍": "蛇盘山涧，黄袍怪盘踞，唐僧遇蛇难。 (34回)",
"所属大洲": "西牛贺洲"
},
{
"地名": "南赡部洲",
"介绍": "南方大洲，东土大唐所在，贪争多杀，佛祖评“口舌凶场，是非恶海”，取经起点。 (1、13回)",
"所属大洲": "南赡部洲"
},
{
"地名": "东土大唐",
"介绍": "唐朝国度，长安为都，唐僧出发地。 (12-13回)",
"所属大洲": "南赡部洲"
},
{
"地名": "长安",
"介绍": "大唐京城，金銮殿，唐僧受旨取经处。 (12回)",
"所属大洲": "南赡部洲"
},
{
"地名": "高老庄",
"介绍": "村庄，猪八戒下凡娶妻处，悟空寻徒地。 (18-19回)",
"所属大洲": "南赡部洲"
},
{
"地名": "流沙河",
"介绍": "宽八百里大河，沙僧为妖食人，唐僧收徒处。 (20-22回)",
"所属大洲": "南赡部洲"
},
{
"地名": "两界山",
"介绍": "南赡西界山，通西牛贺洲，分界处。 (14回)",
"所属大洲": "南赡部洲"
},
{
"地名": "五行山",
"介绍": "两界山峰，压悟空五百载，观音符镇。 (14回)",
"所属大洲": "南赡部洲"
},
{
"地名": "双叉岭",
"介绍": "黑风山岭，鹰愁涧近，唐僧初遇妖。 (16回)",
"所属大洲": "南赡部洲"
},
{
"地名": "黑风山",
"介绍": "顾业山支，黑熊精洞府，唐僧首劫。 (16-17回)",
"所属大洲": "南赡部洲"
},
{
"地名": "黑风洞",
"介绍": "黑风山熊精洞，观音坐骑原居，唐僧被掳。 (16回)",
"所属大洲": "南赡部洲"
},
{
"地名": "蛇盘山",
"介绍": "黄风岭前山，蛇妖盘踞，唐僧遇难。 (21回? 序)",
"所属大洲": "南赡部洲"
},
{
"地名": "鹰愁涧",
"介绍": "乱石山涧，鹰愁坡，虎精夫妇居，唐僧遇虎。 (27回)",
"所属大洲": "南赡部洲"
},
{
"地名": "乱石山",
"介绍": "鹰愁涧山，碧波潭所在，鱼精夫妇妖窟。 (27-28回)",
"所属大洲": "南赡部洲"
},
{
"地名": "碧波潭",
"介绍": "乱石山水潭，鱼篮圣母坐骑妖居，唐僧洗澡劫。 (27回)",
"所属大洲": "南赡部洲"
},
{
"地名": "黄风岭",
"介绍": "平顶山前岭，黄风怪穴，唐僧遇风灾。 (20-21回)",
"所属大洲": "南赡部洲"
},
{
"地名": "黄风洞",
"介绍": "黄风岭狼妖洞，灵吉菩萨坐骑，唐僧被卷。 (20回)",
"所属大洲": "南赡部洲"
},
{
"地名": "平顶山",
"介绍": "黄花观山，狐白鹿精化道士，唐僧误信。 (23-24回)",
"所属大洲": "南赡部洲"
},
{
"地名": "黄花观",
"介绍": "平顶山道观，狐精设坛，唐僧三打白骨精后遇。 (25-26回)",
"所属大洲": "南赡部洲"
},
{
"地名": "宝象国",
"介绍": "象王国，国王失女，唐僧祈福寻女。 (28-31回)",
"所属大洲": "南赡部洲"
},
{
"地名": "黑松林",
"介绍": "宝象国林，黄袍老怪巢，唐僧遇袍怪。 (28回)",
"所属大洲": "南赡部洲"
},
{
"地名": "莲花洞",
"介绍": "黑松林洞，黄袍怪（金圣宫主）居，唐僧被绑。 (28回)",
"所属大洲": "南赡部洲"
},
{
"地名": "浮屠山",
"介绍": "莲花洞山，观音普贤坐骑妖精，唐僧救国王女。 (30回)",
"所属大洲": "南赡部洲"
},
{
"地名": "乌鸡国",
"介绍": "乌鸡观国，国王病目，唐僧医眼除鼠。 (32-35回)",
"所属大洲": "南赡部洲"
},
{
"地名": "车迟国",
"介绍": "车迟道国，三妖阻雨，唐僧斗法收妖。 (36-39回)",
"所属大洲": "南赡部洲"
},
{
"地名": "火焰山",
"介绍": "芭蕉扇灭火山，铁扇公主牛魔地盘，唐僧路阻。 (59-60回)",
"所属大洲": "南赡部洲"
},
{
"地名": "通天河",
"介绍": "九曲黄河，龟背渡河，鲤鱼精兴波，唐僧最后水难。 (47-49回)",
"所属大洲": "南赡部洲"
},
{
"地名": "金山寺",
"介绍": "通天河寺，悟空借宝杖，龟寿僧居。 (47回)",
"所属大洲": "南赡部洲"
},
{
"地名": "玉华山",
"介绍": "玉华门，红叶老人居，唐僧误入城。 (78-80回? 晚期)",
"所属大洲": "南赡部洲"
},
{
"地名": "西海",
"介绍": "西洋大海，孙悟空漂筏过，龙王居。 (2、7回)",
"所属大洲": "跨洲 (西牛贺洲西)"
},
{
"地名": "东海",
"介绍": "东洋大海，龙宫、仙岛多，孙悟空寻龙王。 (3回)",
"所属大洲": "跨洲 (东胜神洲东)"
},
{
"地名": "南海",
"介绍": "南洋海，观音普陀落伽山所在。 (15回)",
"所属大洲": "跨洲 (南赡部洲南)"
},
{
"地名": "北海",
"介绍": "北洋海，少提及，玄冥鱼鲲鹏传说。 (1回)",
"所属大洲": "跨洲 (北俱芦洲北)"
},
{
"地名": "天竺",
"介绍": "西天总称，天竺国别称，取经目的。 (98回)",
"所属大洲": "西牛贺洲"
},
{
"地名": "须弥山",
"介绍": "佛教中心山，四大洲围，佛祖世界轴心。 (1回)",
"所属大洲": "未知 (中央)"
},
{
"地名": "雷音寺",
"介绍": "灵山寺，真经殿，佛祖说法处。 (99回)",
"所属大洲": "西牛贺洲"
},
{
"地名": "兜率天",
"介绍": "天宫道场，太上老君居，炼丹炉压悟空。 (7回)",
"所属大洲": "天界"
},
  {
"地名": "普陀落伽山",
"介绍": "南海菩萨道场，观音大士紫竹林居，唐僧受观音点化及多次求助处。 (12、15回等)",
"所属大洲": "跨洲 (南海)"
},
{
"地名": "盘丝洞",
"介绍": "黄花山盘丝岭洞府，七蜘蛛精巢穴，唐僧师徒遇蛛丝难。 (72回)",
"所属大洲": "西牛贺洲"
},
{
"地名": "琵琶洞",
"介绍": "平顶山琵琶洞，金角银角大王洞府，太上老君紫金红葫芦等法宝处，唐僧斗法收妖。 (32-34回)",
"所属大洲": "南赡部洲"
},
{
"地名": "紫竹林",
"介绍": "普陀落伽山内竹林，善财童子侍菩萨，唐僧师徒听经点化地。 (15回)",
"所属大洲": "跨洲 (南海)"
}
]